eventix/__init__.py
eventix/_version.py
eventix/cli/__init__.py
eventix/client/__init__.py
eventix/client/fastapi/__init__.py
eventix/client/fastapi/router/__init__.py
eventix/client/fastapi/router/eventix.py
eventix/contexts/__init__.py
eventix/depends/__init__.py
eventix/exceptions/__init__.py
eventix/functions/__init__.py
eventix/functions/core.py
eventix/functions/errors.py
eventix/functions/event.py
eventix/functions/eventix_client.py
eventix/functions/fastapi.py
eventix/functions/features.py
eventix/functions/log.py
eventix/functions/metrics.py
eventix/functions/mock.py
eventix/functions/relay.py
eventix/functions/schedule.py
eventix/functions/task.py
eventix/functions/task_scheduler.py
eventix/functions/task_worker.py
eventix/functions/tools.py
eventix/functions/namespace/__init__.py
eventix/functions/namespace/namespace.py
eventix/pydantic/__init__.py
eventix/pydantic/event.py
eventix/pydantic/namespaces.py
eventix/pydantic/pagination.py
eventix/pydantic/relay.py
eventix/pydantic/response_models.py
eventix/pydantic/schedule.py
eventix/pydantic/settings.py
eventix/pydantic/task.py
eventix/pytest/__init__.py
eventix/router/__init__.py
eventix/router/default.py
eventix/router/event.py
eventix/router/metrics.py
eventix/router/namespaces.py
eventix/router/task.py
eventix/router/tasks.py
eventix/tasks/__init__.py
eventix/tasks/cleanup.py
eventix-4.3.3.dist-info/METADATA
eventix-4.3.3.dist-info/WHEEL
eventix-4.3.3.dist-info/entry_points.txt
eventix-4.3.3.dist-info/RECORD
