Metadata-Version: 2.4
Name: eventix
Version: 4.3.3
Author-email: Marco Bartel <bsimpson888@gmail.com>
Requires-Python: <4.0,>=3.13
Requires-Dist: click<9.0.0,>=8.1.7
Requires-Dist: croniter<3.0.0,>=2.0.1
Requires-Dist: lsidentity<2.0.0,>=1.0.2
Requires-Dist: lsrestclient<4.0.0,>=3.0.1
Requires-Dist: pydantic-db-backend-common<3.0.0,>=2.3.1
Requires-Dist: pydantic<3.0.0,>=2.12.0
Requires-Dist: pydash
Requires-Dist: python-dotenv<2.0.0,>=1.0.0
Requires-Dist: toml<0.11.0,>=0.10.2
Requires-Dist: webexception<2.0.0,>=1.0.2
